[
    {
        "name":"Tadpole",
        "sex":1,
        "age":23,
        "height":175,
        "weight":68,
        "address":"陕西省西安市雁塔区高新区锦业路6号（南三环附近）永利国际金融中心"
    },
    {
        "name":"MrChen",
        "sex":1,
        "age":24,
        "height":175,
        "weight":68,
        "address":"浙江省杭州市余杭区思创医惠产业园"
    },
    {
        "name":"MrZhao",
        "sex":0,
        "age":25,
        "height":175,
        "weight":51,
        "address":"陕西省西安市雁塔区响塘文苑"
    },
    {
        "name":"MrQian",
        "sex":1,
        "age":30,
        "height":185,
        "weight":78,
        "address":"陕西省西安市雁塔区创客大厦"
    },
    {
        "name":"MrSun",
        "sex":0,
        "age":28,
        "height":179,
        "weight":70,
        "address":"陕西省西安市雁塔区融城云谷"
    },
    {
        "name":"MrLi",
        "sex":1,
        "age":40,
        "height":180,
        "weight":68,
        "address":"陕西省西安市未央区凤城五路"
    },
    {
        "name":"MrZhou",
        "sex":0,
        "age":38,
        "height":170,
        "weight":68,
        "address":"陕西省西安市曲江新区陕师大附近"
    },
    {
        "name":"MrWu",
        "sex":1,
        "age":40,
        "height":185,
        "weight":80,
        "address":"陕西省西安市雁塔区丈八北路"
    },
    {
        "name":"MrZheng",
        "sex":1,
        "age":29,
        "height":175,
        "weight":66,
        "address":"陕西省西安市雁塔区延平门地铁站附近"
    },
    {
        "name":"MrWang",
        "sex":1,
        "age":29,
        "height":185,
        "weight":80,
        "address":"陕西省西安市雁塔区城西客运站"
    },
    {
        "name":"MrFeng",
        "sex":0,
        "age":25,
        "height":168,
        "weight":60,
        "address":"陕西省西安市长安区长安公园"
    },
    {
        "name":"MrGuo",
        "sex":1,
        "age":25,
        "height":175,
        "weight":74,
        "address":"甘肃省兰州市兰州新区"
    }
]